news_structurize/__init__.py
news_structurize/main.py
news_structurize/prompts.py
news_structurize-2025.12.21125623.dist-info/METADATA
news_structurize-2025.12.21125623.dist-info/WHEEL
news_structurize-2025.12.21125623.dist-info/top_level.txt
news_structurize-2025.12.21125623.dist-info/RECORD
