Metadata-Version: 2.4
Name: news-structurize
Version: 2025.12.21125623
Summary: A new package that takes a news headline or short text snippet as input and returns a structured summary of the key details, such as the person involved, the event, and the financial or business impac
Author-email: news-structurize <hi@eugene.plus>
License: MIT
Project-URL: Homepage, https://github.com/chigwell/news-structurize
Requires-Python: >=3.9
Requires-Dist: langchain-llm7>=0.0.0
Requires-Dist: llmatch-messages>=0.0.0
Requires-Dist: langchain-core>=0.3.0
